cmping.py
cmping-0.17.0.dist-info/licenses/LICENSE
cmping-0.17.0.dist-info/METADATA
cmping-0.17.0.dist-info/WHEEL
cmping-0.17.0.dist-info/entry_points.txt
cmping-0.17.0.dist-info/top_level.txt
cmping-0.17.0.dist-info/RECORD
