Metadata-Version: 2.4
Name: cmping
Version: 0.17.0
Summary: ping messages between chatmail relays
Project-URL: Repository, https://github.com/chatmail/cmping
Project-URL: Changelog, https://github.com/chatmail/cmping/blob/master/CHANGELOG.md
License-File: LICENSE
Requires-Dist: deltachat-rpc-server>=2.24.0
Requires-Dist: deltachat-rpc-client>=2.24.0
Requires-Dist: xdg-base-dirs>=6.0.2
Dynamic: license-file
